stereonet_forge.py
stereonetforge_plot-0.2.1.dist-info/licenses/LICENSE
stereonetforge_plot-0.2.1.dist-info/METADATA
stereonetforge_plot-0.2.1.dist-info/WHEEL
stereonetforge_plot-0.2.1.dist-info/entry_points.txt
stereonetforge_plot-0.2.1.dist-info/top_level.txt
stereonetforge_plot-0.2.1.dist-info/RECORD
