Metadata-Version: 2.4
Name: stereonetforge-plot
Version: 0.2.1
Summary: StereonetForge: dependency-light stereonet plotter for planes (Dip/DipDir) with 1..N groups
Author: Dr. Aram Fathian
License: MIT
Project-URL: Homepage, https://github.com/<your-username>/StereonetForge
Project-URL: Issues, https://github.com/<your-username>/StereonetForge/issues
Keywords: stereonet,geology,structural geology,geoscience,kde,plotting
Classifier: Programming Language :: Python :: 3
Classifier: License :: OSI Approved :: MIT License
Classifier: Intended Audience :: Science/Research
Classifier: Topic :: Scientific/Engineering
Requires-Python: >=3.8
License-File: LICENSE
Requires-Dist: numpy>=1.20
Requires-Dist: pandas>=1.3
Requires-Dist: matplotlib>=3.4
Dynamic: license-file
